odoo9_addon_product_replenishment_cost-9.0.1.0.0-py2.7-nspkg.pth
odoo9_addon_product_replenishment_cost-9.0.1.0.0.dist-info/DESCRIPTION.rst
odoo9_addon_product_replenishment_cost-9.0.1.0.0.dist-info/METADATA
odoo9_addon_product_replenishment_cost-9.0.1.0.0.dist-info/RECORD
odoo9_addon_product_replenishment_cost-9.0.1.0.0.dist-info/WHEEL
odoo9_addon_product_replenishment_cost-9.0.1.0.0.dist-info/metadata.json
odoo9_addon_product_replenishment_cost-9.0.1.0.0.dist-info/namespace_packages.txt
odoo9_addon_product_replenishment_cost-9.0.1.0.0.dist-info/top_level.txt
odoo_addons/product_replenishment_cost/README.rst
odoo_addons/product_replenishment_cost/__init__.py
odoo_addons/product_replenishment_cost/__openerp__.py
odoo_addons/product_replenishment_cost/demo/res_groups.yml
odoo_addons/product_replenishment_cost/i18n/fr.po
odoo_addons/product_replenishment_cost/i18n/nl.po
odoo_addons/product_replenishment_cost/i18n/product_replenishment_cost.pot
odoo_addons/product_replenishment_cost/models/__init__.py
odoo_addons/product_replenishment_cost/models/product_product.py
odoo_addons/product_replenishment_cost/test/cost_price_update.yml
odoo_addons/product_replenishment_cost/views/product_view.xml
